{"assets":{"57D48510E87BCDD89726A871DCA66F65":{"type":"texture","index":262,"assetRequest":{"type":"slide","state":"object","slide":"4AA71B10-1B68-4471-9778-DEB7994F68FB"},"url":{"web":"assets/57D48510E87BCDD89726A871DCA66F65.svg"},"width":203,"height":702},"ACFDA9B5E0C3DD71E181D928C4C5F00C":{"type":"texture","index":269,"assetRequest":{"type":"slide","state":"contents","slide":"4AA71B10-1B68-4471-9778-DEB7994F68FB"},"url":{"web":"assets/ACFDA9B5E0C3DD71E181D928C4C5F00C.svg"},"width":223,"height":728},"599FA0306F28FB263D44AF34511048FE":{"type":"texture","index":263,"assetRequest":{"type":"slide","state":"object","slide":"4AA71B10-1B68-4471-9778-DEB7994F68FB"},"url":{"web":"assets/599FA0306F28FB263D44AF34511048FE.svg"},"width":203,"height":702},"F9E7D73D6BD80DB4AC98BFD8FDDF4F45":{"type":"texture","index":264,"assetRequest":{"type":"slide","state":"shadow","slide":"4AA71B10-1B68-4471-9778-DEB7994F68FB"},"url":{"web":"assets/F9E7D73D6BD80DB4AC98BFD8FDDF4F45.svg"},"width":286,"height":107},"C663FEBBE2A149ADA3EF2E173D2ACC7A":{"type":"texture","index":268,"assetRequest":{"type":"slide","state":"text","slide":"4AA71B10-1B68-4471-9778-DEB7994F68FB"},"url":{"web":"assets/C663FEBBE2A149ADA3EF2E173D2ACC7A.svg"},"width":54,"height":74},"33470E308DE3DCF0A3AAAF1F8BF8E3B9":{"type":"texture","index":265,"assetRequest":{"type":"slide","state":"object","slide":"4AA71B10-1B68-4471-9778-DEB7994F68FB"},"url":{"web":"assets/33470E308DE3DCF0A3AAAF1F8BF8E3B9.svg"},"width":282,"height":103},"54BA1600262A75631CC85138CCEAA410":{"type":"texture","index":259,"assetRequest":{"type":"slide","state":"text","slide":"4AA71B10-1B68-4471-9778-DEB7994F68FB"},"url":{"web":"assets/54BA1600262A75631CC85138CCEAA410.svg"},"width":1277,"height":85},"00D4460B9CC6D80BF8EF481D3234627F":{"type":"texture","index":261,"assetRequest":{"type":"slide","state":"object","slide":"4AA71B10-1B68-4471-9778-DEB7994F68FB"},"url":{"web":"assets/00D4460B9CC6D80BF8EF481D3234627F.svg"},"width":223,"height":728},"C25C25FF361FB24FC35F6B120D2F252D":{"type":"texture","index":258,"assetRequest":{"type":"slide","state":"background","slide":"4AA71B10-1B68-4471-9778-DEB7994F68FB"},"url":{"web":"assets/C25C25FF361FB24FC35F6B120D2F252D.svg"},"width":1920,"height":1080},"117EF153917DCC1E1410C0C28112058B":{"type":"texture","index":260,"assetRequest":{"type":"slide","state":"object","slide":"4AA71B10-1B68-4471-9778-DEB7994F68FB"},"url":{"web":"assets/117EF153917DCC1E1410C0C28112058B.svg"},"width":223,"height":728},"A1351BAA296D2F72A8AE6EF5F69A4484":{"type":"texture","index":267,"assetRequest":{"type":"slide","state":"text","slide":"4AA71B10-1B68-4471-9778-DEB7994F68FB"},"url":{"web":"assets/A1351BAA296D2F72A8AE6EF5F69A4484.svg"},"width":74,"height":74},"C1066BDEFA3BC6BA64ABA6FA37A420D7":{"type":"texture","index":266,"assetRequest":{"type":"slide","state":"object","slide":"4AA71B10-1B68-4471-9778-DEB7994F68FB"},"url":{"web":"assets/C1066BDEFA3BC6BA64ABA6FA37A420D7.svg"},"width":287,"height":113},"C3D35B75E035BF7DEEF86705FB4279A5":{"type":"texture","index":270,"assetRequest":{"type":"slide","state":"contents","slide":"4AA71B10-1B68-4471-9778-DEB7994F68FB"},"url":{"web":"assets/C3D35B75E035BF7DEEF86705FB4279A5.svg"},"width":203,"height":702}},"events":[{"effects":[{"beginTime":0,"baseLayer":{"animations":[],"initialState":{"affineTransform":[1,0,0,1,0,0],"masksToBounds":false,"rotation":0,"scale":1,"position":{"pointX":960,"pointY":540},"width":1920,"sublayerTransform":[1,0,0,0,0,1,0,0,0,0,1,0,0,0,0,1],"contentsRect":{"y":0,"x":0,"width":1,"height":1},"opacity":1,"edgeAntialiasingMask":251658240,"height":1080,"hidden":false,"anchorPoint":{"pointX":0.5,"pointY":0.5}},"objectID":"0","layers":[{"animations":[],"initialState":{"affineTransform":[1,0,0,1,0,0],"masksToBounds":false,"rotation":0,"scale":1,"position":{"pointX":960,"pointY":540},"width":1920,"sublayerTransform":[1,0,0,0,0,1,0,0,0,0,1,-0.0003500791246677598,0,0,0,1],"contentsRect":{"y":0,"x":0,"width":1,"height":1},"opacity":1,"edgeAntialiasingMask":251658240,"height":1080,"hidden":false,"anchorPoint":{"pointX":0.5,"pointY":0.5}},"layers":[{"animations":[{"timeOffset":0,"beginTime":0,"repeatCount":0,"animations":[{"timeOffset":0,"from":{"scalar":0},"beginTime":0,"repeatCount":0,"fillMode":"both","duration":2,"autoreverses":false,"timingFunction":"EaseInEaseOut","property":"zPosition","to":{"scalar":0}}],"fillMode":"both","autoreverses":false,"duration":2}],"initialState":{"affineTransform":[1,0,0,1,0,0],"masksToBounds":false,"rotation":0,"scale":1,"position":{"pointX":960,"pointY":540},"width":1920,"sublayerTransform":[1,0,0,0,0,1,0,0,0,0,1,0,0,0,0,1],"contentsRect":{"y":0,"x":0,"width":1,"height":1},"opacity":1,"edgeAntialiasingMask":251658240,"height":1080,"hidden":false,"anchorPoint":{"pointX":0.5,"pointY":0.5}},"layers":[{"animations":[],"layers":[],"initialState":{"affineTransform":[1,0,0,1,0,0],"masksToBounds":false,"rotation":0,"scale":1,"position":{"pointX":960,"pointY":540},"width":1920,"sublayerTransform":[1,0,0,0,0,1,0,0,0,0,1,0,0,0,0,1],"contentsRect":{"y":0,"x":0,"width":1,"height":1},"opacity":1,"edgeAntialiasingMask":0,"height":1080,"hidden":false,"anchorPoint":{"pointX":0.5,"pointY":0.5}},"texture":"C25C25FF361FB24FC35F6B120D2F252D"}]}]},{"animations":[{"timeOffset":0,"beginTime":0,"repeatCount":0,"animations":[{"timeOffset":0,"from":{"scalar":0.001},"beginTime":0,"repeatCount":0,"fillMode":"both","duration":2,"autoreverses":false,"timingFunction":"EaseInEaseOut","property":"zPosition","to":{"scalar":0.001}}],"fillMode":"both","autoreverses":false,"duration":2}],"initialState":{"affineTransform":[1,0,0,1,0,0],"masksToBounds":false,"rotation":0,"scale":1,"position":{"pointX":960,"pointY":125.2197151184082},"width":1654,"sublayerTransform":[1,0,0,0,0,1,0,0,0,0,1,0,0,0,0,1],"contentsRect":{"y":0,"x":0,"width":1,"height":1},"opacity":1,"edgeAntialiasingMask":251658240,"height":180,"hidden":false,"anchorPoint":{"pointX":0.5,"pointY":0.5}},"layers":[{"animations":[{"timeOffset":0,"beginTime":0,"repeatCount":0,"animations":[{"timeOffset":0,"from":{"texture":"54BA1600262A75631CC85138CCEAA410"},"beginTime":0,"repeatCount":0,"fillMode":"both","duration":2,"autoreverses":false,"timingFunction":"EaseInEaseOut","property":"contents","to":{"texture":"54BA1600262A75631CC85138CCEAA410"}}],"fillMode":"both","autoreverses":false,"duration":2}],"layers":[],"initialState":{"affineTransform":[1,0,0,1,0,0],"masksToBounds":false,"rotation":0,"scale":1,"position":{"pointX":827,"pointY":90},"width":1277,"sublayerTransform":[1,0,0,0,0,1,0,0,0,0,1,0,0,0,0,1],"contentsRect":{"y":0,"x":0,"width":1,"height":1},"opacity":1,"edgeAntialiasingMask":0,"height":85,"hidden":false,"anchorPoint":{"pointX":0.4988253719655442,"pointY":0.6025848837459788}},"texture":"54BA1600262A75631CC85138CCEAA410"}]},{"animations":[{"timeOffset":0,"beginTime":0,"repeatCount":0,"animations":[{"timeOffset":0,"from":{"scalar":0.002},"beginTime":0,"repeatCount":0,"fillMode":"both","duration":2,"autoreverses":false,"timingFunction":"EaseInEaseOut","property":"zPosition","to":{"scalar":0.002}}],"fillMode":"both","autoreverses":false,"duration":2}],"initialState":{"affineTransform":[1,0,0,1,0,0],"masksToBounds":false,"rotation":0,"scale":1,"position":{"pointX":360.3888854980469,"pointY":618},"width":220,"sublayerTransform":[1,0,0,0,0,1,0,0,0,0,1,0,0,0,0,1],"contentsRect":{"y":0,"x":0,"width":1,"height":1},"opacity":1,"edgeAntialiasingMask":251658240,"height":726,"hidden":false,"anchorPoint":{"pointX":0.5,"pointY":0.5}},"layers":[{"animations":[],"layers":[],"initialState":{"affineTransform":[1,0,0,1,0,0],"masksToBounds":false,"rotation":0,"scale":1,"position":{"pointX":110,"pointY":357},"width":223,"sublayerTransform":[1,0,0,0,0,1,0,0,0,0,1,0,0,0,0,1],"contentsRect":{"y":0,"x":0,"width":1,"height":1},"opacity":1,"edgeAntialiasingMask":0,"height":728,"hidden":false,"anchorPoint":{"pointX":0.4995017286907932,"pointY":0.4917582417582417}},"texture":"117EF153917DCC1E1410C0C28112058B"}]},{"animations":[{"timeOffset":0,"beginTime":0,"repeatCount":0,"animations":[{"timeOffset":0,"from":{"scalar":0.003},"beginTime":0,"repeatCount":0,"fillMode":"both","duration":2,"autoreverses":false,"timingFunction":"EaseInEaseOut","property":"zPosition","to":{"scalar":0.003}}],"fillMode":"both","autoreverses":false,"duration":2}],"initialState":{"affineTransform":[1,0,0,1,0,0],"masksToBounds":false,"rotation":0,"scale":1,"position":{"pointX":1573.879150390625,"pointY":618},"width":220,"sublayerTransform":[1,0,0,0,0,1,0,0,0,0,1,0,0,0,0,1],"contentsRect":{"y":0,"x":0,"width":1,"height":1},"opacity":1,"edgeAntialiasingMask":251658240,"height":726,"hidden":false,"anchorPoint":{"pointX":0.5,"pointY":0.5}},"layers":[{"animations":[{"timeOffset":0,"beginTime":0,"repeatCount":0,"animations":[{"timeOffset":0,"from":{"texture":"00D4460B9CC6D80BF8EF481D3234627F"},"beginTime":0,"repeatCount":0,"fillMode":"both","duration":2,"autoreverses":false,"timingFunction":"EaseInEaseOut","property":"contents","to":{"texture":"ACFDA9B5E0C3DD71E181D928C4C5F00C"}},{"timeOffset":0,"from":{"pointX":0,"pointY":0},"beginTime":0,"repeatCount":0,"fillMode":"both","duration":2,"autoreverses":false,"timingFunction":"EaseInEaseOut","property":"transform.translation","to":{"pointX":-1213,"pointY":0}}],"fillMode":"both","autoreverses":false,"duration":2}],"layers":[],"initialState":{"affineTransform":[1,0,0,1,0,0],"masksToBounds":false,"rotation":0,"scale":1,"position":{"pointX":110,"pointY":357},"width":223,"sublayerTransform":[1,0,0,0,0,1,0,0,0,0,1,0,0,0,0,1],"contentsRect":{"y":0,"x":0,"width":1,"height":1},"opacity":1,"edgeAntialiasingMask":0,"height":728,"hidden":false,"anchorPoint":{"pointX":0.5017002259669283,"pointY":0.4917582417582417}},"texture":"00D4460B9CC6D80BF8EF481D3234627F"}]},{"animations":[{"timeOffset":0,"beginTime":0,"repeatCount":0,"animations":[{"timeOffset":0,"from":{"scalar":0.004},"beginTime":0,"repeatCount":0,"fillMode":"both","duration":2,"autoreverses":false,"timingFunction":"EaseInEaseOut","property":"zPosition","to":{"scalar":0.004}}],"fillMode":"both","autoreverses":false,"duration":2}],"initialState":{"affineTransform":[1,0,0,1,0,0],"masksToBounds":false,"rotation":0,"scale":1,"position":{"pointX":1573.879150390625,"pointY":613},"width":200,"sublayerTransform":[1,0,0,0,0,1,0,0,0,0,1,0,0,0,0,1],"contentsRect":{"y":0,"x":0,"width":1,"height":1},"opacity":0.7993881106376648,"edgeAntialiasingMask":251658240,"height":700,"hidden":false,"anchorPoint":{"pointX":0.5,"pointY":0.5}},"layers":[{"animations":[{"timeOffset":0,"beginTime":0,"repeatCount":0,"animations":[{"timeOffset":0,"from":{"texture":"57D48510E87BCDD89726A871DCA66F65"},"beginTime":0,"repeatCount":0,"fillMode":"both","duration":2,"autoreverses":false,"timingFunction":"EaseInEaseOut","property":"contents","to":{"texture":"C3D35B75E035BF7DEEF86705FB4279A5"}},{"timeOffset":0,"from":{"pointX":0,"pointY":0},"beginTime":0,"repeatCount":0,"fillMode":"both","duration":2,"autoreverses":false,"timingFunction":"EaseInEaseOut","property":"transform.translation","to":{"pointX":-1213,"pointY":0}}],"fillMode":"both","autoreverses":false,"duration":2}],"layers":[],"initialState":{"affineTransform":[1,0,0,1,0,0],"masksToBounds":false,"rotation":0,"scale":1,"position":{"pointX":99.99999999999999,"pointY":350},"width":203,"sublayerTransform":[1,0,0,0,0,1,0,0,0,0,1,0,0,0,0,1],"contentsRect":{"y":0,"x":0,"width":1,"height":1},"opacity":1,"edgeAntialiasingMask":0,"height":702,"hidden":false,"anchorPoint":{"pointX":0.5018677359144088,"pointY":0.5}},"texture":"57D48510E87BCDD89726A871DCA66F65"}]},{"animations":[{"timeOffset":0,"beginTime":0,"repeatCount":0,"animations":[{"timeOffset":0,"from":{"scalar":0.005},"beginTime":0,"repeatCount":0,"fillMode":"both","duration":2,"autoreverses":false,"timingFunction":"EaseInEaseOut","property":"zPosition","to":{"scalar":0.005}}],"fillMode":"both","autoreverses":false,"duration":2}],"initialState":{"affineTransform":[1,0,0,1,0,0],"masksToBounds":false,"rotation":0,"scale":1,"position":{"pointX":360.3888854980469,"pointY":613},"width":200,"sublayerTransform":[1,0,0,0,0,1,0,0,0,0,1,0,0,0,0,1],"contentsRect":{"y":0,"x":0,"width":1,"height":1},"opacity":0.7969569563865662,"edgeAntialiasingMask":251658240,"height":700,"hidden":false,"anchorPoint":{"pointX":0.5,"pointY":0.5}},"layers":[{"animations":[],"layers":[],"initialState":{"affineTransform":[1,0,0,1,0,0],"masksToBounds":false,"rotation":0,"scale":1,"position":{"pointX":100,"pointY":350},"width":203,"sublayerTransform":[1,0,0,0,0,1,0,0,0,0,1,0,0,0,0,1],"contentsRect":{"y":0,"x":0,"width":1,"height":1},"opacity":1,"edgeAntialiasingMask":0,"height":702,"hidden":false,"anchorPoint":{"pointX":0.4994526379214132,"pointY":0.5}},"texture":"599FA0306F28FB263D44AF34511048FE"}]},{"animations":[{"timeOffset":0,"beginTime":0,"repeatCount":0,"animations":[{"timeOffset":0,"from":{"scalar":0.006},"beginTime":0,"repeatCount":0,"fillMode":"both","duration":2,"autoreverses":false,"timingFunction":"EaseInEaseOut","property":"zPosition","to":{"scalar":0.006}}],"fillMode":"both","autoreverses":false,"duration":2}],"initialState":{"affineTransform":[1,0,0,1,0,0],"masksToBounds":false,"rotation":0,"scale":1,"position":{"pointX":488.1175231933594,"pointY":767.4900512695312},"width":278.82470703125,"sublayerTransform":[1,0,0,0,0,1,0,0,0,0,1,0,0,0,0,1],"contentsRect":{"y":0,"x":0,"width":1,"height":1},"opacity":1,"edgeAntialiasingMask":251658240,"height":100,"hidden":false,"anchorPoint":{"pointX":0.5,"pointY":0.5}},"layers":[{"animations":[{"timeOffset":0,"beginTime":0,"repeatCount":0,"animations":[{"timeOffset":0,"from":{"scalar":0.5},"beginTime":0,"repeatCount":0,"fillMode":"forwards","duration":0.6666,"autoreverses":false,"timingFunction":"EaseInEaseOut","property":"opacity","to":{"scalar":0}},{"timeOffset":0,"from":{"scalar":true},"beginTime":0.6666,"repeatCount":0,"fillMode":"forwards","property":"hidden","autoreverses":false,"duration":1.3334,"to":{"scalar":true}}],"fillMode":"both","autoreverses":false,"duration":2}],"layers":[],"initialState":{"affineTransform":[-1,0,0,-1,0,0],"masksToBounds":false,"rotation":3.141592653589793,"scale":1,"position":{"pointX":139.412353515625,"pointY":52},"width":286,"sublayerTransform":[1,0,0,0,0,1,0,0,0,0,1,0,0,0,0,1],"contentsRect":{"y":0,"x":0,"width":1,"height":1},"opacity":0.5,"edgeAntialiasingMask":0,"height":107,"hidden":false,"anchorPoint":{"pointX":0.5004109202565014,"pointY":0.4999070212105725}},"texture":"F9E7D73D6BD80DB4AC98BFD8FDDF4F45"}]},{"animations":[{"timeOffset":0,"beginTime":0,"repeatCount":0,"animations":[{"timeOffset":0,"from":{"scalar":0.007},"beginTime":0,"repeatCount":0,"fillMode":"both","duration":2,"autoreverses":false,"timingFunction":"EaseInEaseOut","property":"zPosition","to":{"scalar":0.007}}],"fillMode":"both","autoreverses":false,"duration":2}],"initialState":{"affineTransform":[1,0,0,1,0,0],"masksToBounds":false,"rotation":0,"scale":1,"position":{"pointX":488.1175231933594,"pointY":767.4900512695312},"width":278.82470703125,"sublayerTransform":[1,0,0,0,0,1,0,0,0,0,1,0,0,0,0,1],"contentsRect":{"y":0,"x":0,"width":1,"height":1},"opacity":1,"edgeAntialiasingMask":251658240,"height":100,"hidden":false,"anchorPoint":{"pointX":0.5,"pointY":0.5}},"layers":[{"animations":[{"timeOffset":0,"beginTime":0,"repeatCount":0,"animations":[{"timeOffset":0,"from":{"scalar":1},"beginTime":0,"repeatCount":0,"fillMode":"forwards","duration":0.6666,"autoreverses":false,"timingFunction":"EaseInEaseOut","property":"opacity","to":{"scalar":0}},{"timeOffset":0,"from":{"scalar":true},"beginTime":0.6666,"repeatCount":0,"fillMode":"forwards","property":"hidden","autoreverses":false,"duration":1.3334,"to":{"scalar":true}}],"fillMode":"both","autoreverses":false,"duration":2}],"layers":[],"initialState":{"affineTransform":[-1,0,0,-1,0,0],"masksToBounds":false,"rotation":3.141592653589793,"scale":1,"position":{"pointX":139.412353515625,"pointY":50},"width":282,"sublayerTransform":[1,0,0,0,0,1,0,0,0,0,1,0,0,0,0,1],"contentsRect":{"y":0,"x":0,"width":1,"height":1},"opacity":1,"edgeAntialiasingMask":0,"height":103,"hidden":false,"anchorPoint":{"pointX":0.5004167489126219,"pointY":0.4999034103837985}},"texture":"33470E308DE3DCF0A3AAAF1F8BF8E3B9"}]},{"animations":[{"timeOffset":0,"beginTime":0,"repeatCount":0,"animations":[{"timeOffset":0,"from":{"scalar":0.008},"beginTime":0,"repeatCount":0,"fillMode":"both","duration":2,"autoreverses":false,"timingFunction":"EaseInEaseOut","property":"zPosition","to":{"scalar":0.008}}],"fillMode":"both","autoreverses":false,"duration":2}],"initialState":{"affineTransform":[1,0,0,1,0,0],"masksToBounds":false,"rotation":0,"scale":1,"position":{"pointX":1342.470092773438,"pointY":767.4900512695312},"width":278.82470703125,"sublayerTransform":[1,0,0,0,0,1,0,0,0,0,1,0,0,0,0,1],"contentsRect":{"y":0,"x":0,"width":1,"height":1},"opacity":1,"edgeAntialiasingMask":251658240,"height":100,"hidden":false,"anchorPoint":{"pointX":0.5,"pointY":0.5}},"layers":[{"animations":[{"timeOffset":0,"beginTime":0,"repeatCount":0,"animations":[{"timeOffset":0,"from":{"scalar":1},"beginTime":0,"repeatCount":0,"fillMode":"forwards","duration":0.6666,"autoreverses":false,"timingFunction":"EaseInEaseOut","property":"opacity","to":{"scalar":0}},{"timeOffset":0,"from":{"scalar":true},"beginTime":0.6666,"repeatCount":0,"fillMode":"forwards","property":"hidden","autoreverses":false,"duration":1.3334,"to":{"scalar":true}}],"fillMode":"both","autoreverses":false,"duration":2}],"layers":[],"initialState":{"affineTransform":[1,0,0,1,0,0],"masksToBounds":false,"rotation":0,"scale":1,"position":{"pointX":139.412353515625,"pointY":50},"width":287,"sublayerTransform":[1,0,0,0,0,1,0,0,0,0,1,0,0,0,0,1],"contentsRect":{"y":0,"x":0,"width":1,"height":1},"opacity":1,"edgeAntialiasingMask":0,"height":113,"hidden":false,"anchorPoint":{"pointX":0.4998957936356707,"pointY":0.4999119581374447}},"texture":"C1066BDEFA3BC6BA64ABA6FA37A420D7"}]},{"animations":[{"timeOffset":0,"beginTime":0,"repeatCount":0,"animations":[{"timeOffset":0,"from":{"scalar":0.009000000000000001},"beginTime":0,"repeatCount":0,"fillMode":"both","duration":2,"autoreverses":false,"timingFunction":"EaseInEaseOut","property":"zPosition","to":{"scalar":0.009000000000000001}}],"fillMode":"both","autoreverses":false,"duration":2}],"initialState":{"affineTransform":[1,0,0,1,0,0],"masksToBounds":false,"rotation":0,"scale":1,"position":{"pointX":687.1713256835938,"pointY":767.4900512695312},"width":82.40000009536743,"sublayerTransform":[1,0,0,0,0,1,0,0,0,0,1,0,0,0,0,1],"contentsRect":{"y":0,"x":0,"width":1,"height":1},"opacity":1,"edgeAntialiasingMask":251658240,"height":107.7999234199524,"hidden":false,"anchorPoint":{"pointX":0.5,"pointY":0.5}},"layers":[{"animations":[{"timeOffset":0,"beginTime":0,"repeatCount":0,"animations":[{"timeOffset":0,"from":{"scalar":1},"beginTime":0,"repeatCount":0,"fillMode":"forwards","duration":0.6666,"autoreverses":false,"timingFunction":"EaseInEaseOut","property":"opacity","to":{"scalar":0}},{"timeOffset":0,"from":{"scalar":true},"beginTime":0.6666,"repeatCount":0,"fillMode":"forwards","property":"hidden","autoreverses":false,"duration":1.3334,"to":{"scalar":true}}],"fillMode":"both","autoreverses":false,"duration":2}],"layers":[],"initialState":{"affineTransform":[1,0,0,1,0,0],"masksToBounds":false,"rotation":0,"scale":1,"position":{"pointX":41.20000000000005,"pointY":53.89996331930161},"width":74,"sublayerTransform":[1,0,0,0,0,1,0,0,0,0,1,0,0,0,0,1],"contentsRect":{"y":0,"x":0,"width":1,"height":1},"opacity":1,"edgeAntialiasingMask":0,"height":74,"hidden":false,"anchorPoint":{"pointX":0.5023152112960821,"pointY":0.6147304443088738}},"texture":"A1351BAA296D2F72A8AE6EF5F69A4484"}]},{"animations":[{"timeOffset":0,"beginTime":0,"repeatCount":0,"animations":[{"timeOffset":0,"from":{"scalar":0.01},"beginTime":0,"repeatCount":0,"fillMode":"both","duration":2,"autoreverses":false,"timingFunction":"EaseInEaseOut","property":"zPosition","to":{"scalar":0.01}}],"fillMode":"both","autoreverses":false,"duration":2}],"initialState":{"affineTransform":[1,0,0,1,0,0],"masksToBounds":false,"rotation":0,"scale":1,"position":{"pointX":1156.135498046875,"pointY":767.4900512695312},"width":70.39999961853027,"sublayerTransform":[1,0,0,0,0,1,0,0,0,0,1,0,0,0,0,1],"contentsRect":{"y":0,"x":0,"width":1,"height":1},"opacity":1,"edgeAntialiasingMask":251658240,"height":107.7999234199524,"hidden":false,"anchorPoint":{"pointX":0.5,"pointY":0.5}},"layers":[{"animations":[{"timeOffset":0,"beginTime":0,"repeatCount":0,"animations":[{"timeOffset":0,"from":{"scalar":1},"beginTime":0,"repeatCount":0,"fillMode":"forwards","duration":0.6666,"autoreverses":false,"timingFunction":"EaseInEaseOut","property":"opacity","to":{"scalar":0}},{"timeOffset":0,"from":{"scalar":true},"beginTime":0.6666,"repeatCount":0,"fillMode":"forwards","property":"hidden","autoreverses":false,"duration":1.3334,"to":{"scalar":true}}],"fillMode":"both","autoreverses":false,"duration":2}],"layers":[],"initialState":{"affineTransform":[1,0,0,1,0,0],"masksToBounds":false,"rotation":0,"scale":1,"position":{"pointX":35.20000000000005,"pointY":53.89996331930161},"width":54,"sublayerTransform":[1,0,0,0,0,1,0,0,0,0,1,0,0,0,0,1],"contentsRect":{"y":0,"x":0,"width":1,"height":1},"opacity":1,"edgeAntialiasingMask":0,"height":74,"hidden":false,"anchorPoint":{"pointX":0.4654721895853687,"pointY":0.6147304443088738}},"texture":"C663FEBBE2A149ADA3EF2E173D2ACC7A"}]}]},"effects":[],"duration":2,"type":"transition","name":"apple:magic-move-implied-motion-path","objectID":"0"}],"automaticPlay":false,"hyperlinks":[],"accessibility":[{"text":"CALCULATE ACCURACY","targetRectangle":{"y":69.2197151184082,"x":319.752,"width":1280.496,"height":112.4559178352356}},{"text":"e2副本.png","targetRectangle":{"y":255,"x":250.3888854980469,"width":220,"height":726}},{"text":"edm1.png","targetRectangle":{"y":263,"x":1473.879150390625,"width":200,"height":700}},{"text":"A","targetRectangle":{"y":717.5900895595551,"x":650.47132563591,"width":73.39999999999998,"height":99.79992663860321}},{"text":"B","targetRectangle":{"y":717.5900895595551,"x":1125.43549823761,"width":61.40000000000009,"height":99.79992663860321}},{"text":"edm2.png","targetRectangle":{"y":263,"x":260.3888854980469,"width":200,"height":700}},{"text":"e.png","targetRectangle":{"y":255,"x":1463.879150390625,"width":220,"height":726}}],"baseLayer":{"animations":[],"initialState":{"affineTransform":[1,0,0,1,0,0],"masksToBounds":false,"rotation":0,"scale":1,"position":{"pointX":960,"pointY":540},"width":1920,"sublayerTransform":[1,0,0,0,0,1,0,0,0,0,1,0,0,0,0,1],"contentsRect":{"y":0,"x":0,"width":1,"height":1},"opacity":1,"edgeAntialiasingMask":251658240,"height":1080,"hidden":false,"anchorPoint":{"pointX":0.5,"pointY":0.5}},"objectID":"0","layers":[{"animations":[],"initialState":{"affineTransform":[1,0,0,1,0,0],"masksToBounds":false,"rotation":0,"scale":1,"position":{"pointX":960,"pointY":540},"width":1920,"sublayerTransform":[1,0,0,0,0,1,0,0,0,0,1,-0.0003500791246677598,0,0,0,1],"contentsRect":{"y":0,"x":0,"width":1,"height":1},"opacity":1,"edgeAntialiasingMask":251658240,"height":1080,"hidden":false,"anchorPoint":{"pointX":0.5,"pointY":0.5}},"layers":[{"animations":[],"initialState":{"affineTransform":[1,0,0,1,0,0],"masksToBounds":false,"rotation":0,"scale":1,"position":{"pointX":960,"pointY":540},"width":1920,"sublayerTransform":[1,0,0,0,0,1,0,0,0,0,1,0,0,0,0,1],"contentsRect":{"y":0,"x":0,"width":1,"height":1},"opacity":1,"edgeAntialiasingMask":251658240,"height":1080,"hidden":false,"anchorPoint":{"pointX":0.5,"pointY":0.5}},"layers":[{"animations":[],"layers":[],"initialState":{"affineTransform":[1,0,0,1,0,0],"masksToBounds":false,"rotation":0,"scale":1,"position":{"pointX":960,"pointY":540},"width":1920,"sublayerTransform":[1,0,0,0,0,1,0,0,0,0,1,0,0,0,0,1],"contentsRect":{"y":0,"x":0,"width":1,"height":1},"opacity":1,"edgeAntialiasingMask":0,"height":1080,"hidden":false,"anchorPoint":{"pointX":0.5,"pointY":0.5}},"texture":"C25C25FF361FB24FC35F6B120D2F252D"}]}]},{"animations":[],"initialState":{"affineTransform":[1,0,0,1,0,0],"masksToBounds":false,"rotation":0,"scale":1,"position":{"pointX":960,"pointY":125.2197151184082},"width":1654,"sublayerTransform":[1,0,0,0,0,1,0,0,0,0,1,0,0,0,0,1],"contentsRect":{"y":0,"x":0,"width":1,"height":1},"opacity":1,"edgeAntialiasingMask":251658240,"height":180,"hidden":false,"anchorPoint":{"pointX":0.5,"pointY":0.5}},"layers":[{"animations":[],"layers":[],"initialState":{"affineTransform":[1,0,0,1,0,0],"masksToBounds":false,"rotation":0,"scale":1,"position":{"pointX":827,"pointY":90},"width":1277,"sublayerTransform":[1,0,0,0,0,1,0,0,0,0,1,0,0,0,0,1],"contentsRect":{"y":0,"x":0,"width":1,"height":1},"opacity":1,"edgeAntialiasingMask":0,"height":85,"hidden":false,"anchorPoint":{"pointX":0.4988253719655442,"pointY":0.6025848837459788}},"texture":"54BA1600262A75631CC85138CCEAA410"}]},{"animations":[],"initialState":{"affineTransform":[1,0,0,1,0,0],"masksToBounds":false,"rotation":0,"scale":1,"position":{"pointX":360.3888854980469,"pointY":618},"width":220,"sublayerTransform":[1,0,0,0,0,1,0,0,0,0,1,0,0,0,0,1],"contentsRect":{"y":0,"x":0,"width":1,"height":1},"opacity":1,"edgeAntialiasingMask":251658240,"height":726,"hidden":false,"anchorPoint":{"pointX":0.5,"pointY":0.5}},"layers":[{"animations":[],"layers":[],"initialState":{"affineTransform":[1,0,0,1,0,0],"masksToBounds":false,"rotation":0,"scale":1,"position":{"pointX":110,"pointY":357},"width":223,"sublayerTransform":[1,0,0,0,0,1,0,0,0,0,1,0,0,0,0,1],"contentsRect":{"y":0,"x":0,"width":1,"height":1},"opacity":1,"edgeAntialiasingMask":0,"height":728,"hidden":false,"anchorPoint":{"pointX":0.4995017286907932,"pointY":0.4917582417582417}},"texture":"117EF153917DCC1E1410C0C28112058B"}]},{"animations":[],"initialState":{"affineTransform":[1,0,0,1,0,0],"masksToBounds":false,"rotation":0,"scale":1,"position":{"pointX":1573.879150390625,"pointY":618},"width":220,"sublayerTransform":[1,0,0,0,0,1,0,0,0,0,1,0,0,0,0,1],"contentsRect":{"y":0,"x":0,"width":1,"height":1},"opacity":1,"edgeAntialiasingMask":251658240,"height":726,"hidden":false,"anchorPoint":{"pointX":0.5,"pointY":0.5}},"layers":[{"animations":[],"layers":[],"initialState":{"affineTransform":[1,0,0,1,0,0],"masksToBounds":false,"rotation":0,"scale":1,"position":{"pointX":110,"pointY":357},"width":223,"sublayerTransform":[1,0,0,0,0,1,0,0,0,0,1,0,0,0,0,1],"contentsRect":{"y":0,"x":0,"width":1,"height":1},"opacity":1,"edgeAntialiasingMask":0,"height":728,"hidden":false,"anchorPoint":{"pointX":0.5017002259669283,"pointY":0.4917582417582417}},"texture":"00D4460B9CC6D80BF8EF481D3234627F"}]},{"animations":[],"initialState":{"affineTransform":[1,0,0,1,0,0],"masksToBounds":false,"rotation":0,"scale":1,"position":{"pointX":1573.879150390625,"pointY":613},"width":200,"sublayerTransform":[1,0,0,0,0,1,0,0,0,0,1,0,0,0,0,1],"contentsRect":{"y":0,"x":0,"width":1,"height":1},"opacity":0.7993881106376648,"edgeAntialiasingMask":251658240,"height":700,"hidden":false,"anchorPoint":{"pointX":0.5,"pointY":0.5}},"layers":[{"animations":[],"layers":[],"initialState":{"affineTransform":[1,0,0,1,0,0],"masksToBounds":false,"rotation":0,"scale":1,"position":{"pointX":99.99999999999999,"pointY":350},"width":203,"sublayerTransform":[1,0,0,0,0,1,0,0,0,0,1,0,0,0,0,1],"contentsRect":{"y":0,"x":0,"width":1,"height":1},"opacity":1,"edgeAntialiasingMask":0,"height":702,"hidden":false,"anchorPoint":{"pointX":0.5018677359144088,"pointY":0.5}},"texture":"57D48510E87BCDD89726A871DCA66F65"}]},{"animations":[],"initialState":{"affineTransform":[1,0,0,1,0,0],"masksToBounds":false,"rotation":0,"scale":1,"position":{"pointX":360.3888854980469,"pointY":613},"width":200,"sublayerTransform":[1,0,0,0,0,1,0,0,0,0,1,0,0,0,0,1],"contentsRect":{"y":0,"x":0,"width":1,"height":1},"opacity":0.7969569563865662,"edgeAntialiasingMask":251658240,"height":700,"hidden":false,"anchorPoint":{"pointX":0.5,"pointY":0.5}},"layers":[{"animations":[],"layers":[],"initialState":{"affineTransform":[1,0,0,1,0,0],"masksToBounds":false,"rotation":0,"scale":1,"position":{"pointX":100,"pointY":350},"width":203,"sublayerTransform":[1,0,0,0,0,1,0,0,0,0,1,0,0,0,0,1],"contentsRect":{"y":0,"x":0,"width":1,"height":1},"opacity":1,"edgeAntialiasingMask":0,"height":702,"hidden":false,"anchorPoint":{"pointX":0.4994526379214132,"pointY":0.5}},"texture":"599FA0306F28FB263D44AF34511048FE"}]},{"animations":[],"initialState":{"affineTransform":[1,0,0,1,0,0],"masksToBounds":false,"rotation":0,"scale":1,"position":{"pointX":488.1175231933594,"pointY":767.4900512695312},"width":278.82470703125,"sublayerTransform":[1,0,0,0,0,1,0,0,0,0,1,0,0,0,0,1],"contentsRect":{"y":0,"x":0,"width":1,"height":1},"opacity":1,"edgeAntialiasingMask":251658240,"height":100,"hidden":false,"anchorPoint":{"pointX":0.5,"pointY":0.5}},"layers":[{"animations":[],"layers":[],"initialState":{"affineTransform":[-1,0,0,-1,0,0],"masksToBounds":false,"rotation":3.141592653589793,"scale":1,"position":{"pointX":139.412353515625,"pointY":52},"width":286,"sublayerTransform":[1,0,0,0,0,1,0,0,0,0,1,0,0,0,0,1],"contentsRect":{"y":0,"x":0,"width":1,"height":1},"opacity":0.5,"edgeAntialiasingMask":0,"height":107,"hidden":false,"anchorPoint":{"pointX":0.5004109202565014,"pointY":0.4999070212105725}},"texture":"F9E7D73D6BD80DB4AC98BFD8FDDF4F45"}]},{"animations":[],"initialState":{"affineTransform":[1,0,0,1,0,0],"masksToBounds":false,"rotation":0,"scale":1,"position":{"pointX":488.1175231933594,"pointY":767.4900512695312},"width":278.82470703125,"sublayerTransform":[1,0,0,0,0,1,0,0,0,0,1,0,0,0,0,1],"contentsRect":{"y":0,"x":0,"width":1,"height":1},"opacity":1,"edgeAntialiasingMask":251658240,"height":100,"hidden":false,"anchorPoint":{"pointX":0.5,"pointY":0.5}},"layers":[{"animations":[],"layers":[],"initialState":{"affineTransform":[-1,0,0,-1,0,0],"masksToBounds":false,"rotation":3.141592653589793,"scale":1,"position":{"pointX":139.412353515625,"pointY":50},"width":282,"sublayerTransform":[1,0,0,0,0,1,0,0,0,0,1,0,0,0,0,1],"contentsRect":{"y":0,"x":0,"width":1,"height":1},"opacity":1,"edgeAntialiasingMask":0,"height":103,"hidden":false,"anchorPoint":{"pointX":0.5004167489126219,"pointY":0.4999034103837985}},"texture":"33470E308DE3DCF0A3AAAF1F8BF8E3B9"}]},{"animations":[],"initialState":{"affineTransform":[1,0,0,1,0,0],"masksToBounds":false,"rotation":0,"scale":1,"position":{"pointX":1342.470092773438,"pointY":767.4900512695312},"width":278.82470703125,"sublayerTransform":[1,0,0,0,0,1,0,0,0,0,1,0,0,0,0,1],"contentsRect":{"y":0,"x":0,"width":1,"height":1},"opacity":1,"edgeAntialiasingMask":251658240,"height":100,"hidden":false,"anchorPoint":{"pointX":0.5,"pointY":0.5}},"layers":[{"animations":[],"layers":[],"initialState":{"affineTransform":[1,0,0,1,0,0],"masksToBounds":false,"rotation":0,"scale":1,"position":{"pointX":139.412353515625,"pointY":50},"width":287,"sublayerTransform":[1,0,0,0,0,1,0,0,0,0,1,0,0,0,0,1],"contentsRect":{"y":0,"x":0,"width":1,"height":1},"opacity":1,"edgeAntialiasingMask":0,"height":113,"hidden":false,"anchorPoint":{"pointX":0.4998957936356707,"pointY":0.4999119581374447}},"texture":"C1066BDEFA3BC6BA64ABA6FA37A420D7"}]},{"animations":[],"initialState":{"affineTransform":[1,0,0,1,0,0],"masksToBounds":false,"rotation":0,"scale":1,"position":{"pointX":687.1713256835938,"pointY":767.4900512695312},"width":82.40000009536743,"sublayerTransform":[1,0,0,0,0,1,0,0,0,0,1,0,0,0,0,1],"contentsRect":{"y":0,"x":0,"width":1,"height":1},"opacity":1,"edgeAntialiasingMask":251658240,"height":107.7999234199524,"hidden":false,"anchorPoint":{"pointX":0.5,"pointY":0.5}},"layers":[{"animations":[],"layers":[],"initialState":{"affineTransform":[1,0,0,1,0,0],"masksToBounds":false,"rotation":0,"scale":1,"position":{"pointX":41.20000000000005,"pointY":53.89996331930161},"width":74,"sublayerTransform":[1,0,0,0,0,1,0,0,0,0,1,0,0,0,0,1],"contentsRect":{"y":0,"x":0,"width":1,"height":1},"opacity":1,"edgeAntialiasingMask":0,"height":74,"hidden":false,"anchorPoint":{"pointX":0.5023152112960821,"pointY":0.6147304443088738}},"texture":"A1351BAA296D2F72A8AE6EF5F69A4484"}]},{"animations":[],"initialState":{"affineTransform":[1,0,0,1,0,0],"masksToBounds":false,"rotation":0,"scale":1,"position":{"pointX":1156.135498046875,"pointY":767.4900512695312},"width":70.39999961853027,"sublayerTransform":[1,0,0,0,0,1,0,0,0,0,1,0,0,0,0,1],"contentsRect":{"y":0,"x":0,"width":1,"height":1},"opacity":1,"edgeAntialiasingMask":251658240,"height":107.7999234199524,"hidden":false,"anchorPoint":{"pointX":0.5,"pointY":0.5}},"layers":[{"animations":[],"layers":[],"initialState":{"affineTransform":[1,0,0,1,0,0],"masksToBounds":false,"rotation":0,"scale":1,"position":{"pointX":35.20000000000005,"pointY":53.89996331930161},"width":54,"sublayerTransform":[1,0,0,0,0,1,0,0,0,0,1,0,0,0,0,1],"contentsRect":{"y":0,"x":0,"width":1,"height":1},"opacity":1,"edgeAntialiasingMask":0,"height":74,"hidden":false,"anchorPoint":{"pointX":0.4654721895853687,"pointY":0.6147304443088738}},"texture":"C663FEBBE2A149ADA3EF2E173D2ACC7A"}]}]}}]}